collective.honeypot-4.0.0-py3.13-nspkg.pth
collective/honeypot/__init__.py
collective/honeypot/auto.py
collective/honeypot/browser.py
collective/honeypot/config.py
collective/honeypot/configure.zcml
collective/honeypot/eventsubscribers.py
collective/honeypot/fixes.zcml
collective/honeypot/honeypot.pt
collective/honeypot/interfaces.py
collective/honeypot/testing.py
collective/honeypot/utils.py
collective/honeypot/locales/__init__.py
collective/honeypot/locales/collective.honeypot.pot
collective/honeypot/locales/update.sh
collective/honeypot/locales/es/LC_MESSAGES/collective.honeypot.po
collective/honeypot/locales/it/LC_MESSAGES/collective.honeypot.po
collective/honeypot/plone5/__init__.py
collective/honeypot/plone5/configure.zcml
collective/honeypot/plone5/patches.py
collective/honeypot/plone5/overrides/plone.app.z3cform.templates.macros.pt
collective/honeypot/plone60/__init__.py
collective/honeypot/plone60/configure.zcml
collective/honeypot/plone60/patches.py
collective/honeypot/plone60/overrides/plone.app.z3cform.templates.macros.pt
collective/honeypot/plone61/__init__.py
collective/honeypot/plone61/configure.zcml
collective/honeypot/plone61/patches.py
collective/honeypot/plone61/overrides/plone.app.z3cform.templates.macros.pt
collective/honeypot/tests/__init__.py
collective/honeypot/tests/test_functional.py
collective/honeypot/tests/test_restapi.py
collective/honeypot/tests/test_unit.py
collective/honeypot/z3cform/__init__.py
collective/honeypot/z3cform/configure.zcml
collective/honeypot/z3cform/honeypotextender.py
collective/honeypot/z3cform/widget.py
collective/honeypot/z3cform/widget_display.pt
collective_honeypot-4.0.0.dist-info/METADATA
collective_honeypot-4.0.0.dist-info/WHEEL
collective_honeypot-4.0.0.dist-info/entry_points.txt
collective_honeypot-4.0.0.dist-info/namespace_packages.txt
collective_honeypot-4.0.0.dist-info/top_level.txt
collective_honeypot-4.0.0.dist-info/RECORD
